Workbook

Sheet Matriz Ckeck LIst
B3: MATRIZ PARA COMPROBACIÓN REQUERIMIENTOS DE CALIDAD DE PROYECTO ACADEMICO
B5: SISTEMA: | E5: Sistema de planificación y seguimiento de eventos sociales y deportivos del Club de Suboficiales Retirados (EVENTUAL)
B6: Requerimientos Funcionales
B7: Nº | C7: CRITERIOS DE CALIDAD (Documento/Requerimientos) | E7: Status Nivel de Acuerdo | F7: RF02 Gestionar Miembros | M7: Status Nivel de Acuerdo | N7: CU-005: Confirmar Asistencia al Evento
F9: CU-001 Agregar Socio | H9: CU-002 Asignar rol | J9: CU-003 Modificar socio | L9: CU-004 Desactivar socio
B10: 1 | C10: Agreed | E10: OK | F10: 1. Videoconferencia de la entrevista 2. Minuta de la entrevista 3. Aceptación por videoconferencia | G10: OK | H10: 1. Videoconferencia de la entrevista 2. Minuta de la entrevista 3. Aceptación por videoconferencia | I10: OK | J10: 1. Videoconferencia de la entrevista 2. Minuta de la entrevista 3. Aceptación por videoconferencia | K10: OK | L10: 1. Videoconferencia de la entrevista 2. Minuta de la entrevista 3. Aceptación por videoconferencia | M10: OK | N10: 1. Videoconferencia de la entrevista 2. Minuta de la entrevista 3. Aceptación por videoconferencia
B11: 2 | C11: Ranked | E11: OK | F11: 1. En la descripción del caso de Uso se especifica la prioridad Alta | G11: NOK | H11: 1. La prioridad esta declarada como "media", y al ser la asignación del rol, deberia estar como alta, pues al asignar el rol, se define los accesos del usuario. | I11: OK | J11: Prioridad declarada como "Media", algo correcto ya que editar la información de un socio es algo ocasional. | K11: OK | L11: 1. Prioridad declarada como "Alta". | M11: OK | N11: 1. Prioridad declarada como "Media", algo que estaria correcto debido a que la confirmación de la asistencia, da mayor fiabilidad de que sigan asistiendo a los próximos eventos.
B12: 3 | C12: Unambiguos | E12: OK | F12: 1. Redacción en lenguaje claro. 2. El tutor y el equipo interpretan de igual manera el caso de uso | G12: OK | H12: 1. Tiene una redacción en un lenguje claro | I12: OK | J12: Describe la acción de actualizar datos existentes. | K12: OK | L12: 1. Define claramente que el socio queda "inactivo", no borrado. | M12: OK | N12: 1. Establece plazos (15 días) y uso de WhatsApp muy claros.
B13: 4 | C13: Valid and up-to date | E13: OK | F13: 1. Toda nueva información ha sido incorporada, se han incorporado los últimos cambios pedidos luego del feedback realizado por el cliente | G13: OK | H13: 1. Toda nueva información ha sido incorporada, se han incorporado los últimos cambios pedidos luego del feedback realizado por el cliente | I13: OK | J13: 1. Toda nueva información ha sido incorporada, se han incorporado los últimos cambios pedidos luego del feedback realizado por el cliente | K13: NOK | L13: 1. Es la forma moderna de manejar bajas en sistemas contables. | M13: OK | N13: Resuelve el problema actual de confirmaciones informales.
B14: 5 | C14: Correct | E14: OK | F14: 1. Está alineado con los objetivos del sistema. 2. Refleja lo que realmente necesita el cliente. | G14: NOK | H14: 1. No esta acoplado mucho a los objetivos del sistema, ya que al tener prioridad media, no estan dando la suficiente importancia a un dato escencial del sistema | I14: OK | J14: 1. La edición de perfiles es una función lógica en cualquier gestión. | K14: OK | L14: 1. Está alineado con los objetivos del sistema. 2. Refleja lo que realmente necesita el cliente. | M14: OK | N14: 1. La lógica de notificaciones automáticas es ideal para el club.
B15: 6 | C15: Consisten | E15: OK | F15: 1. Documentación basada en modelos: Diagrama de Casos de Uso 2. Usa términos definidos previamente. | G15: OK | H15: 1. Documentación basada en modelos: Diagrama de Casos de Uso 2. Usa términos definidos previamente. | I15: OK | J15: 1. Mantiene la integridad con los datos creados en el CU-001.. | K15: OK | L15: El estado "inactivo" es coherente con el flujo descrito en comentarios (el presidente puede desactivar el socio | M15: OK | N15: 1. Se alinea con los roles de Socio y Secretario.
B16: 7 | C16: Verifiable | E16: OK | F16: 1. El cumplimiento de este requisito puede ser verificado. Los pasos están bien definidos, y puedes probar el flujo del ingreso de los datos y ek estado del socio. | G16: OK | H16: 1. Filtros por tipo de evento son testables. 2. Notificaciones en tiempos configurados son verificables. 3. Mensaje de "no hay eventos" es comprobable. | I16: OK | J16: 1. Basta con editar un campo y verificar que el cambio persista. | K16: OK | L16: 1. Se verifica al intentar loguear a un usuario desactivado. | M16: OK | N16: 1. Se puede verificar el envío del mensaje y el registro final.
B17: 8 | C17: Realizable | E17: OK | F17: 1. Funcionalidad tomada en cuenta dentro de la estimación del costo del proyecto ($1827) 2. No se ha desarrollado | G17: OK | H17: 1. Funcionalidad tomada en cuenta dentro de la estimación del costo del proyecto ($1827) 2. No se ha desarrollado | I17: OK | J17: Es una actualización (Update) básica en la base de datos. | K17: OK | L17: 2. Es un simple cambio de estado lógico (true/false) en la BD. | M17: OK | N17: Factible mediante APIs de mensajería y Flutter.
B18: 9 | C18: Traceable | E18: NOK | F18: 1. No se refleja en claro las relaciones con lode demás requisitos q deben estar asociados | G18: OK | H18: Vinculado al requerimiento de control de acceso por niveles.. | I18: OK | J18: Se vincula a la gestión continua de la membresía del club. | K18: NOK | L18: No referencia los CU posteriores si es que el socio tiene eventos a cargo o no referencia q sucederá con ellos. | M18: OK | N18: 1. Ereferencia a los casos de uso y da las opciones correctas para afirmar o negar la asistencia, y permite realizar mejoras a futuro
B19: 10 | C19: Complete | E19: NOK | F19: 1. Falta el flujo de error si la cédula ya está registrada o es inválida | G19: NOK | H19: 1.No aclara si un socio puede tener dos roles al mismo tiempo. | I19: NOK | J19: 1. No define qué campos no se pueden editar (ej. la cédula. | K19: NOK | L19: 1. No detalla qué pasa con sus deudas o asistencias pendienteso. | M19: NOK | N19: 1. No define límites de cupo ni proceso de cancelación.
B20: 11 | C20: Understandability | E20: OK | F20: 1. Se involucra al cliente 2. Existe glosario de términos | G20: OK | H20: 1. Se involucra al cliente 2. Existe glosario de términos | I20: OK | J20: 1. Se involucra al cliente 2. Existe glosario de términos | K20: OK | L20: 1. Se involucra al cliente 2. Existe glosario de términos | M20: OK | N20: 1. Se involucra al cliente 2. Existe glosario de términos

Sheet MODELO LISTA DE COMPROBACION 1
A1: SISTEMA: | C1: Sistema de planificación y seguimiento de eventos sociales y deportivos del Club de Suboficiales Retirados (EVENTUAL)
A2: FECHA: | C2: 46155
A3: AUTOR: | C3: Alex Cuzco
A4: REQUERIMIENTOS EVALUADOS : | C4: CU-001 Agregar socio
A6: CONTENIDO
A7: No. | B7: Pregunta | C7: SI | D7: NO
A8: 1 | B8: Todos los requerimientos relevantes se han documentado? | D8: X
A9: 2 | B9: Se han implementado las funciones requeridas? | C9: X
A10: 3 | B10: Existe algún mecanismo que permita seguir el impacto de dicho requerimiento a lo largo del resto de las actividades del ciclo productivo.? | D10: X
A11: 4 | B11: El origen de cada requerimento individual está claro ? | C11: X
A12: 5 | B12: Que tan facil es devolverse a los requerimientos? | C12: X
A13: 6 | B13: Los requerimientos reflejan las necesidades y deseos del cliente? | C13: X
A14: 7 | B14: No hay contradicciones entre los requerimientos? | C14: X
A15: 8 | B15: El requerimiento que se esta especificando contribuye a alcanzar un objetivo definido ? | C15: X
A16: 9 | B16: Existe un proceso acotado (en plazo y presupuesto) que permita determinar que el sistema construido satisface lo descrito en el propio requerimiento? | C16: X
A17: SUMATORIA: | C17: =COUNTA('MODELO LISTA DE COMPROBACION 1'!$C$8:$C$16) -> 7 | D17: =COUNTA('MODELO LISTA DE COMPROBACION 1'!$D$8:$D$16) -> 2
A18: PORCENTAJE : | C18: =C17/9 -> 0.77777778 | D18: =D17/9 -> 0.22222222
A20: DOCUMENTACIÓN
A21: No. | B21: Pregunta | C21: SI | D21: NO
A22: 1 | B22: Aplica un estandar para la documetación de requerimiento? | C22: X
A23: 2 | B23: Cumple con la estructura definida por el estandar? | C23: X
A24: 3 | B24: Utiliza un Glosario de términos normalizado? | C24: X
A25: 4 | B25: Los requerimientos Funcionales estan sujetos a una única interpretación? | C25: X
A26: 5 | B26: El modelo aplicado cumple con la sintaxis? | C26: X
A27: SUMATORIA: | C27: =COUNTA('MODELO LISTA DE COMPROBACION 1'!$C$22:$C$26) -> 5 | D27: =COUNTA('MODELO LISTA DE COMPROBACION 1'!$D$22:$D$26) -> 0
A28: PORCENTAJE : | C28: =C27/5 -> 1 | D28: =D27/5 -> 0
A30: NIVEL DE ACUERDO
A31: No. | B31: Pregunta | C31: SI | D31: NO
A32: 1 | B32: Todos los requerimientos han sido acordados con todos los interesados? | C32: X
A33: 2 | B33: Todos los requerimientos modificados han sido acordados por todos los implicados? | C33: X
A34: 3 | B34: Han sido resueltos todos los conflictos conocidos respectos de los requerimientos? | D34: X
A35: SUMATORIA: | C35: =COUNTA('MODELO LISTA DE COMPROBACION 1'!$C$32:$C$34) -> 2 | D35: =COUNTA('MODELO LISTA DE COMPROBACION 1'!$D$32:$D$34) -> 1
A36: PORCENTAJE : | C36: =C35/3 -> 0.66666667 | D36: =D35/3 -> 0.33333333
B40: RESUMEN
B41: CONTENIDO | C41: 78
B42: DOCUMENTACIÓN | C42: 100
B43: NIVEL DE ACUERDO | C43: 67

Sheet MODELO LISTA DE COMPROBACION 2
A1: SISTEMA: | C1: Sistema de planificación y seguimiento de eventos sociales y deportivos del Club de Suboficiales Retirados (EVENTUAL)
A2: FECHA: | C2: 46155
A3: AUTOR: | C3: Alex Cuzco
A4: REQUERIMIENTOS EVALUADOS : | C4: CU-003 Asignar rol
A6: CONTENIDO
A7: No. | B7: Pregunta | C7: SI | D7: NO
A8: 1 | B8: Todos los requerimientos relevantes se han documentado? | C8: X
A9: 2 | B9: Se han implementado las funciones requeridas? | C9: X
A10: 3 | B10: Existe algún mecanismo que permita seguir el impacto de dicho requerimiento a lo largo del resto de las actividades del ciclo productivo.? | D10: X
A11: 4 | B11: El origen de cada requerimento individual está claro ? | C11: X
A12: 5 | B12: Que tan facil es devolverse a los requerimientos? | C12: X
A13: 6 | B13: Los requerimientos reflejan las necesidades y deseos del cliente? | C13: X
A14: 7 | B14: No hay contradicciones entre los requerimientos? | C14: X
A15: 8 | B15: El requerimiento que se esta especificando contribuye a alcanzar un objetivo definido ? | C15: X
A16: 9 | B16: Existe un proceso acotado (en plazo y presupuesto) que permita determinar que el sistema construido satisface lo descrito en el propio requerimiento? | C16: X
A17: SUMATORIA: | C17: =COUNTA('MODELO LISTA DE COMPROBACION 2'!$C$8:$C$16) -> 8 | D17: =COUNTA('MODELO LISTA DE COMPROBACION 2'!$D$8:$D$16) -> 1
A18: PORCENTAJE : | C18: =C17/9 -> 0.88888889 | D18: =D17/9 -> 0.11111111
A20: DOCUMENTACIÓN
A21: No. | B21: Pregunta | C21: SI | D21: NO
A22: 1 | B22: Aplica un estandar para la documetación de requerimiento? | C22: X
A23: 2 | B23: Cumple con la estructura definida por el estandar? | C23: X
A24: 3 | B24: Utiliza un Glosario de términos normalizado? | C24: X
A25: 4 | B25: Los requerimientos Funcionales estan sujetos a una única interpretación? | D25: X
A26: 5 | B26: El modelo aplicado cumple con la sintaxis? | C26: X
A27: SUMATORIA: | C27: 4 | D27: 1
A28: PORCENTAJE : | C28: =C27/5 -> 0.8 | D28: =D27/5 -> 0.2
A30: NIVEL DE ACUERDO
A31: No. | B31: Pregunta | C31: SI | D31: NO
A32: 1 | B32: Todos los requerimientos han sido acordados con todos los interesados? | C32: X
A33: 2 | B33: Todos los requerimientos modificados han sido acordados por todos los implicados? | C33: X
A34: 3 | B34: Han sido resueltos todos los conflictos conocidos respectos de los requerimientos? | D34: X
A35: SUMATORIA: | C35: 2 | D35: 1
A36: PORCENTAJE : | C36: =C35/3 -> 0.66666667 | D36: =D35/3 -> 0.33333333
B40: RESUMEN
B41: CONTENIDO | C41: 89
B42: DOCUMENTACIÓN | C42: 80
B43: NIVEL DE ACUERDO | C43: 67

Sheet MODELO LISTA DE COMPROBACION 3
A1: SISTEMA: | C1: Sistema de planificación y seguimiento de eventos sociales y deportivos del Club de Suboficiales Retirados (EVENTUAL)
A2: FECHA: | C2: 46155
A3: AUTOR: | C3: Pablo Domínguez
A4: REQUERIMIENTOS EVALUADOS : | C4: CU-003: Modificar socio
A6: CONTENIDO
A7: No. | B7: Pregunta | C7: SI | D7: NO
A8: 1 | B8: Todos los requerimientos relevantes se han documentado? | C8: X
A9: 2 | B9: Se han implementado las funciones requeridas? | C9: X
A10: 3 | B10: Existe algún mecanismo que permita seguir el impacto de dicho requerimiento a lo largo del resto de las actividades del ciclo productivo.? | D10: X
A11: 4 | B11: El origen de cada requerimento individual está claro ? | C11: X
A12: 5 | B12: Que tan facil es devolverse a los requerimientos? | C12: X
A13: 6 | B13: Los requerimientos reflejan las necesidades y deseos del cliente? | C13: X
A14: 7 | B14: No hay contradicciones entre los requerimientos? | C14: X
A15: 8 | B15: El requerimiento que se esta especificando contribuye a alcanzar un objetivo definido ? | C15: X
A16: 9 | B16: Existe un proceso acotado (en plazo y presupuesto) que permita determinar que el sistema construido satisface lo descrito en el propio requerimiento? | C16: X
A17: SUMATORIA: | C17: 8 | D17: 1
A18: PORCENTAJE : | C18: =C17/9 -> 0.88888889 | D18: =D17/9 -> 0.11111111
A20: DOCUMENTACIÓN
A21: No. | B21: Pregunta | C21: SI | D21: NO
A22: 1 | B22: Aplica un estandar para la documetación de requerimiento? | C22: X
A23: 2 | B23: Cumple con la estructura definida por el estandar? | C23: X
A24: 3 | B24: Utiliza un Glosario de términos normalizado? | C24: X
A25: 4 | B25: Los requerimientos Funcionales estan sujetos a una única interpretación? | C25: X
A26: 5 | B26: El modelo aplicado cumple con la sintaxis? | C26: X
A27: SUMATORIA: | C27: 5 | D27: 0
A28: PORCENTAJE : | C28: =C27/5 -> 1 | D28: =D27/5 -> 0
A30: NIVEL DE ACUERDO
A31: No. | B31: Pregunta | C31: SI | D31: NO
A32: 1 | B32: Todos los requerimientos han sido acordados con todos los interesados? | C32: X
A33: 2 | B33: Todos los requerimientos modificados han sido acordados por todos los implicados? | C33: X
A34: 3 | B34: Han sido resueltos todos los conflictos conocidos respectos de los requerimientos? | C34: X
A35: SUMATORIA: | C35: 3 | D35: 0
A36: PORCENTAJE : | C36: =C35/3 -> 1 | D36: =D35/3 -> 0
B40: RESUMEN
B41: CONTENIDO | C41: 89
B42: DOCUMENTACIÓN | C42: 100
B43: NIVEL DE ACUERDO | C43: 100

Sheet MODELO LISTA DE COMPROBACION 4
A1: SISTEMA: | C1: Sistema de planificación y seguimiento de eventos sociales y deportivos del Club de Suboficiales Retirados (EVENTUAL)
A2: FECHA: | C2: 46155
A3: AUTOR: | C3: Dylan Alvarado
A4: REQUERIMIENTOS EVALUADOS : | C4: CU-004: Desactivar socio
A6: CONTENIDO
A7: No. | B7: Pregunta | C7: SI | D7: NO
A8: 1 | B8: Todos los requerimientos relevantes se han documentado? | C8: X
A9: 2 | B9: Se han implementado las funciones requeridas? | C9: X
A10: 3 | B10: Existe algún mecanismo que permita seguir el impacto de dicho requerimiento a lo largo del resto de las actividades del ciclo productivo.? | D10: X
A11: 4 | B11: El origen de cada requerimento individual está claro ? | C11: X
A12: 5 | B12: Que tan facil es devolverse a los requerimientos? | C12: X
A13: 6 | B13: Los requerimientos reflejan las necesidades y deseos del cliente? | C13: X
A14: 7 | B14: No hay contradicciones entre los requerimientos? | C14: X
A15: 8 | B15: El requerimiento que se esta especificando contribuye a alcanzar un objetivo definido ? | D15: X
A16: 9 | B16: Existe un proceso acotado (en plazo y presupuesto) que permita determinar que el sistema construido satisface lo descrito en el propio requerimiento? | C16: X
A17: SUMATORIA: | C17: 7 | D17: 2
A18: PORCENTAJE : | C18: =C17/9 -> 0.77777778 | D18: =D17/9 -> 0.22222222
A20: DOCUMENTACIÓN
A21: No. | B21: Pregunta | C21: SI | D21: NO
A22: 1 | B22: Aplica un estandar para la documetación de requerimiento? | C22: X
A23: 2 | B23: Cumple con la estructura definida por el estandar? | C23: X
A24: 3 | B24: Utiliza un Glosario de términos normalizado? | C24: X
A25: 4 | B25: Los requerimientos Funcionales estan sujetos a una única interpretación? | D25: X
A26: 5 | B26: El modelo aplicado cumple con la sintaxis? | C26: X
A27: SUMATORIA: | C27: 4 | D27: 0
A28: PORCENTAJE : | C28: =C27/5 -> 0.8 | D28: =D27/5 -> 0
A30: NIVEL DE ACUERDO
A31: No. | B31: Pregunta | C31: SI | D31: NO
A32: 1 | B32: Todos los requerimientos han sido acordados con todos los interesados? | C32: X
A33: 2 | B33: Todos los requerimientos modificados han sido acordados por todos los implicados? | C33: X
A34: 3 | B34: Han sido resueltos todos los conflictos conocidos respectos de los requerimientos? | D34: X
A35: SUMATORIA: | C35: 2 | D35: 0
A36: PORCENTAJE : | C36: =C35/3 -> 0.66666667 | D36: =D35/3 -> 0
B40: RESUMEN
B41: CONTENIDO | C41: 78
B42: DOCUMENTACIÓN | C42: 80
B43: NIVEL DE ACUERDO | C43: 67

Sheet MODELO LISTA DE COMPROBACION 5
A1: SISTEMA: | C1: Sistema de planificación y seguimiento de eventos sociales y deportivos del Club de Suboficiales Retirados (EVENTUAL)
A2: FECHA: | C2: 46155
A3: AUTOR: | C3: Dylan Alvarado
A4: REQUERIMIENTOS EVALUADOS : | C4: CU005: Confirmar asistencia al evento
A6: CONTENIDO
A7: No. | B7: Pregunta | C7: SI | D7: NO
A8: 1 | B8: Todos los requerimientos relevantes se han documentado? | C8: X
A9: 2 | B9: Se han implementado las funciones requeridas? | C9: X
A10: 3 | B10: Existe algún mecanismo que permita seguir el impacto de dicho requerimiento a lo largo del resto de las actividades del ciclo productivo.? | D10: X
A11: 4 | B11: El origen de cada requerimento individual está claro ? | C11: X
A12: 5 | B12: Que tan facil es devolverse a los requerimientos? | C12: X
A13: 6 | B13: Los requerimientos reflejan las necesidades y deseos del cliente? | C13: X
A14: 7 | B14: No hay contradicciones entre los requerimientos? | C14: X
A15: 8 | B15: El requerimiento que se esta especificando contribuye a alcanzar un objetivo definido ? | C15: X
A16: 9 | B16: Existe un proceso acotado (en plazo y presupuesto) que permita determinar que el sistema construido satisface lo descrito en el propio requerimiento? | C16: X
A17: SUMATORIA: | C17: 8 | D17: 1
A18: PORCENTAJE : | C18: =C17/9 -> 0.88888889 | D18: =D17/9 -> 0.11111111
A20: DOCUMENTACIÓN
A21: No. | B21: Pregunta | C21: SI | D21: NO
A22: 1 | B22: Aplica un estandar para la documetación de requerimiento? | C22: X
A23: 2 | B23: Cumple con la estructura definida por el estandar? | C23: X
A24: 3 | B24: Utiliza un Glosario de términos normalizado? | C24: X
A25: 4 | B25: Los requerimientos Funcionales estan sujetos a una única interpretación? | C25: X
A26: 5 | B26: El modelo aplicado cumple con la sintaxis? | C26: X
A27: SUMATORIA: | C27: 5 | D27: 0
A28: PORCENTAJE : | C28: =C27/5 -> 1 | D28: =D27/5 -> 0
A30: NIVEL DE ACUERDO
A31: No. | B31: Pregunta | C31: SI | D31: NO
A32: 1 | B32: Todos los requerimientos han sido acordados con todos los interesados? | C32: X
A33: 2 | B33: Todos los requerimientos modificados han sido acordados por todos los implicados? | C33: X
A34: 3 | B34: Han sido resueltos todos los conflictos conocidos respectos de los requerimientos? | C34: X
A35: SUMATORIA: | C35: 3 | D35: 0
A36: PORCENTAJE : | C36: =C35/3 -> 1 | D36: =D35/3 -> 0
B40: RESUMEN
B41: CONTENIDO | C41: 89
B42: DOCUMENTACIÓN | C42: 100
B43: NIVEL DE ACUERDO | C43: 100

Sheet RECOMENDACIONES
A2: CU-001 Agregar Socio
A3: PREGUNTA | B3: RECOMENDACIÓN
A4: ¿Se han definido claramente las relaciones de este caso de uso con otros procesos del sistema, como asignar roles, modificar o desactivar socios? | B4: Es importante incorporar referencias explícitas a los casos de uso relacionados para asegurar una correcta trazabilidad y comprensión del flujo completo de gestión de miembros.
A5: ¿El caso de uso contempla qué sucede cuando la cédula ingresada ya existe o posee un formato inválido? | B5: Debe añadirse un flujo alternativo que detalle las validaciones de cédula duplicada o incorrecta, incluyendo mensajes de error y acciones permitidas al usuario.
A9: CU-002 Asignar Rol
A10: PREGUNTA | B10: RECOMENDACIÓN
A11: ¿La prioridad del caso de uso refleja realmente la importancia de la asignación de roles dentro del sistema? | B11: Se recomienda cambiar la prioridad de “Media” a “Alta”, ya que la asignación de roles controla los permisos y accesos de los usuarios dentro de la plataforma.
A12: ¿La funcionalidad de asignar roles se encuentra completamente alineada con los objetivos principales del sistema y la gestión de accesos? | B12: Es importante reforzar la relación de este caso de uso con la seguridad y control de acceso del sistema, destacando su impacto dentro de la administración de usuarios.
A13: ¿El caso de uso especifica claramente si un socio puede tener más de un rol asignado simultáneamente? | B13: Es necesario definir las reglas de negocio relacionadas con la asignación múltiple de roles, indicando restricciones, validaciones y posibles conflictos entre permisos.
A17: CU-003 Modificar Socio
A18: PREGUNTA | B18: RECOMENDACIÓN
A19: ¿Se encuentran definidos los campos que no pueden ser modificados por motivos de seguridad o integridad? | B19: Es importante especificar qué datos son editables y cuáles deben permanecer bloqueados, como la cédula o identificadores únicos del socio.
A23: CU-004 Desactivar Socio
A24: PREGUNTA | B24: RECOMENDACIÓN
A25: ¿El caso de uso refleja adecuadamente prácticas actuales para la gestión de bajas y estados inactivos dentro del sistema? | B25: Se recomienda actualizar y ampliar la descripción del proceso de desactivación para incluir escenarios modernos de gestión administrativa y control de usuarios inactivos.
A26: ¿Se hace referencia a los casos de uso o procesos que podrían verse afectados por la desactivación de un socio? | B26: Es importante relacionar este caso de uso con otros procesos dependientes, como eventos organizados, asistencias registradas o actividades administrativas asociadas al socio.
A27: ¿Se ha definido qué ocurrirá con las obligaciones pendientes del socio, como deudas, asistencias o eventos asociados? | B27: El caso de uso debe detallar cómo se manejarán las responsabilidades pendientes y los registros históricos antes de completar la desactivación del socio.
A31: CU-005 Confirmar Asistencia al Evento
A32: PREGUNTA | B32: RECOMENDACIÓN
A33: ¿El caso de uso define claramente cómo se gestionarán los límites de cupo, cancelaciones y validaciones de asistencia? | B33: Se recomienda incluir reglas de negocio relacionadas con cupos máximos, listas de espera, cancelaciones y restricciones para asegurar un control adecuado de la asistencia a eventos.
